Metadata-Version: 2.1
Name: odoo13-addon-sale-stock-available-info-popup
Version: 13.0.1.0.3
Summary: Adds an 'Available to promise' quantity to the popover shown in sale order line that display stock info of the product
Home-page: https://github.com/OCA/stock-logistics-warehouse
Author: Tecnativa, Odoo Community Association (OCA)
Author-email: support@odoo-community.org
License: AGPL-3
Platform: UNKNOWN
Classifier: Programming Language :: Python
Classifier: Framework :: Odoo
Classifier: Framework :: Odoo :: 13.0
Classifier: License :: OSI Approved :: GNU Affero General Public License v3
Requires-Python: >=3.5
Requires-Dist: odoo13-addon-stock-available
Requires-Dist: odoo (<13.1dev,>=13.0a)
